manage.py
cpu_checker/__init__.py
cpu_checker/asgi.py
cpu_checker/settings.py
cpu_checker/urls.py
cpu_checker/wsgi.py
cpu_checker_service/__init__.py
cpu_checker_service/admin.py
cpu_checker_service/apps.py
cpu_checker_service/models.py
cpu_checker_service/orm.py
cpu_checker_service/tests.py
cpu_checker_service/views.py
cpu_checker_service/migrations/0001_initial.py
cpu_checker_service/migrations/__init__.py
cpu_checker_service/static/script.js
cpu_checker_service/static/styles.css
cpu_checker_service/templates/index.html
cpu_utilization_monitoring-0.1.3.dist-info/METADATA
cpu_utilization_monitoring-0.1.3.dist-info/WHEEL
cpu_utilization_monitoring-0.1.3.dist-info/top_level.txt
cpu_utilization_monitoring-0.1.3.dist-info/RECORD
