Metadata-Version: 2.1
Name: cpu-utilization-monitoring
Version: 0.1.3
Summary: Тестовое задание для carbon soft.
Home-page: https://github.com/zeleniyToster/test_task_carbon_soft
Download-URL: https://github.com/zeleniyToster/test_task_carbon_soft/archive/refs/heads/master.zip
Author: Basov Ivan
Author-email: demon_cuc@mail.ru
Requires-Python: >=3.10.4
Requires-Dist: asgiref (==3.8.1)
Requires-Dist: Django (==4.2.10)
Requires-Dist: sqlparse (==0.5.0)
Requires-Dist: typing-extensions (==4.11.0)
Requires-Dist: tzdata (==2024.1)
